monnaie_converter/__init__.py
monnaie_converter/apps.py
monnaie_converter/forms.py
monnaie_converter/urls.py
monnaie_converter/views.py
monnaie_converter/static/monnaie_converter/style.css
monnaie_converter/templates/monnaie_converter/converter.html
django_monnaie_converter-0.1.3.dist-info/LICENSE
django_monnaie_converter-0.1.3.dist-info/METADATA
django_monnaie_converter-0.1.3.dist-info/WHEEL
django_monnaie_converter-0.1.3.dist-info/top_level.txt
django_monnaie_converter-0.1.3.dist-info/RECORD
