Metadata-Version: 2.1
Name: django-monnaie-converter
Version: 0.1.3
Summary: Un convertisseur de monnaies simple pour Django
Home-page: https://github.com/toncompte/django-monnaie-converter
Author: Nicosidick
Author-email: abou210traore@gmail.com
License: MIT
Platform: UNKNOWN
Classifier: Programming Language :: Python :: 3
Classifier: Framework :: Django
Classifier: License :: OSI Approved :: MIT License
Classifier: Operating System :: OS Independent
Requires-Python: >=3.6
License-File: LICENSE
Requires-Dist: Django (>=3.0)
